aspect_ratio/__init__.py
aspect_ratio/aspect_ratio_calculate.py
aspect_ratio-0.5.0.dist-info/WHEEL
aspect_ratio-0.5.0.dist-info/METADATA
aspect_ratio-0.5.0.dist-info/RECORD
